tiktok_signer/__init__.py
tiktok_signer/example.py
tiktok_signer/signer.py
tiktok_signer/lib/__init__.py
tiktok_signer/lib/argus.py
tiktok_signer/lib/gorgon.py
tiktok_signer/lib/ladon.py
tiktok_signer/lib/stub.py
tiktok_signer/lib/ttencrypt.py
tiktok_signer/lib/data/dword.json
tiktok_signer/lib/utils/__init__.py
tiktok_signer/lib/utils/protobuf.py
tiktok_signer/lib/utils/simon.py
tiktok_signer/lib/utils/sm3.py
tiktok_signer/lib/utils/stub.py
tiktok_signer-1.3.1.dist-info/METADATA
tiktok_signer-1.3.1.dist-info/WHEEL
tiktok_signer-1.3.1.dist-info/licenses/LICENSE
tiktok_signer-1.3.1.dist-info/RECORD
