Metadata-Version: 2.4
Name: tiktok-signer
Version: 1.3.1
Summary: TikTok Android API authentication signature generator
Project-URL: Homepage, https://github.com/iqbalmh18/tiktok-signer
Project-URL: Repository, https://github.com/iqbalmh18/tiktok-signer
Project-URL: Issues, https://github.com/iqbalmh18/tiktok-signer/issues
Author: iqbalmh18
License: MIT
License-File: LICENSE
Keywords: android,api,authentication,signature,tiktok
Classifier: Development Status :: 4 - Beta
Classifier: Intended Audience :: Developers
Classifier: License :: OSI Approved :: MIT License
Classifier: Operating System :: OS Independent
Classifier: Programming Language :: Python :: 3
Classifier: Programming Language :: Python :: 3.10
Classifier: Programming Language :: Python :: 3.11
Classifier: Programming Language :: Python :: 3.12
Classifier: Programming Language :: Python :: 3.13
Classifier: Topic :: Internet
Classifier: Topic :: Software Development :: Libraries :: Python Modules
Requires-Python: >=3.10
Requires-Dist: pycryptodome>=3.23.0
Requires-Dist: twine>=6.2.0
Provides-Extra: dev
Requires-Dist: mypy>=1.19.0; extra == 'dev'
Requires-Dist: pytest-cov>=7.0.0; extra == 'dev'
Requires-Dist: pytest>=9.0.0; extra == 'dev'
Requires-Dist: ruff>=0.14.0; extra == 'dev'
